glBooklet/__init__.py
glBooklet/__main__.py
glBooklet/glbooklet.py
glBooklet/mainwindow_rc.py
glBooklet/mainwindow_ui.py
glBooklet/images/QtIcon.png
glBooklet/images/application-exit.svg
glBooklet/images/archive-insert.svg
glBooklet/images/document-export.svg
glBooklet/images/document-import.png
glBooklet/images/document-import.svg
glBooklet/images/glBooklet.png
glBooklet/images/help-about.svg
glBooklet/images/help-donate.svg
glBooklet/images/logo32x32.png
glBooklet/resources/glBooklet.desktop
glBooklet/resources/mainwindow.qrc
glBooklet/resources/mainwindow.ui
glBooklet/resources/test_pdf.odg
glBooklet/resources/test_pdf.pdf
glBooklet-0.0.3.dist-info/LICENSE
glBooklet-0.0.3.dist-info/METADATA
glBooklet-0.0.3.dist-info/WHEEL
glBooklet-0.0.3.dist-info/entry_points.txt
glBooklet-0.0.3.dist-info/top_level.txt
glBooklet-0.0.3.dist-info/RECORD
