Metadata-Version: 2.1
Name: glBooklet
Version: 0.0.3
Summary: Converts PDFs to printable booklet
Home-page: https://git.gallochri.com/gallochri/glBooklet
Author: gallochri
Author-email: chri@gallochri.com
License: GPLv3
Download-URL: https://git.gallochri.com/gallochri/glBooklet.git
Keywords: pdf,book,print
Platform: any
Classifier: Development Status :: 2 - Pre-Alpha
Classifier: Environment :: X11 Applications :: Qt
Classifier: Intended Audience :: End Users/Desktop
Classifier: License :: OSI Approved :: GNU General Public License v3 (GPLv3)
Classifier: Natural Language :: English
Classifier: Operating System :: OS Independent
Classifier: Programming Language :: Python :: 3.7
Classifier: Topic :: Utilities
Classifier: Topic :: Printing
Provides: g
Provides: l
Provides: B
Provides: o
Provides: o
Provides: k
Provides: l
Provides: e
Provides: t
Requires-Python: >=3.4
Requires-Dist: PyQt5
Requires-Dist: pyPdf2
